extractlib/__init__.py
extractlib/classification/__init__.py
extractlib/classification/prep_utils.py
extractlib/classification/utils/__init__.py
extractlib/classification/utils/keywords.py
extractlib/document/__init__.py
extractlib/document/page.py
extractlib/document/process.py
extractlib/document/table.py
extractlib/document/utils.py
extractlib/exceptions/__init__.py
extractlib/models/__init__.py
extractlib/models/table.py
extractlib/ner/__init__.py
extractlib/nlp/__init__.py
extractlib/nlp/pre_process.py
extractlib/nlp/stopwords.py
extractlib/settings/__init__.py
extractlib/settings/config.py
extractlib/utils/json_utils.py
extractlib/utils/temp_dir.py
requirements/requirements.txt
insights_extractor-0.1.6.dist-info/LICENSE
insights_extractor-0.1.6.dist-info/METADATA
insights_extractor-0.1.6.dist-info/WHEEL
insights_extractor-0.1.6.dist-info/top_level.txt
insights_extractor-0.1.6.dist-info/RECORD
