Metadata-Version: 2.1
Name: insights-extractor
Version: 0.1.6
Summary: Efficient PDF analysis, text extraction, preprocessing, and pattern recognition with customizable configurations and utilities.
Author-email: Trae Moore <trae.dev@gmail.com>
Project-URL: Homepage, https://github.com/traemoore/insights-extractor
Project-URL: Tests, https://github.com/traemoore/insights-extractor-test
Project-URL: Bug Tracker, https://github.com/traemoore/insights-extractor/issues
Keywords: nltk,spaCy,Pymupdf,Camelot,OpenCV,Ghostscript,insight-extractor,pdf extraction,pdf data extraction,pdf data,classification,keyword extraction
Classifier: Programming Language :: Python :: 3
Classifier: License :: OSI Approved :: MIT License
Classifier: Operating System :: OS Independent
Requires-Python: >=3.7
License-File: LICENSE
Requires-Dist: camelot-py (==0.11.0) ; python_version >= "3.6"
Requires-Dist: opencv-python (==4.7.0.72) ; python_version >= "3.6"
Requires-Dist: ghostscript (==0.7) ; python_version >= "3.6"
Requires-Dist: spacy (==3.5.2) ; python_version >= "3.7"
Requires-Dist: nltk (==3.8.1) ; python_version >= "3.7"
Requires-Dist: PyMuPDF (==1.21.1) ; python_version >= "3.7"
